markdownify/__init__.py
markdownify/settings.py
markdownify/templatetags/__init__.py
markdownify/templatetags/markdownify_tags.py
markdownify/tests/__init__.py
markdownify/tests/settings.py
markdownify/utils/__init__.py
markdownify/utils/markdownify.py
markdowny/__init__.py
markdowny/settings.py
markdowny/templatetags/__init__.py
markdowny/templatetags/markdowny_tags.py
markdowny/tests/__init__.py
markdowny/tests/settings.py
markdowny/tests/test_markdowny.py
markdowny/utils/__init__.py
markdowny/utils/markdowny.py
django_markdowny-0.2.4.dist-info/LICENSE
django_markdowny-0.2.4.dist-info/METADATA
django_markdowny-0.2.4.dist-info/WHEEL
django_markdowny-0.2.4.dist-info/top_level.txt
django_markdowny-0.2.4.dist-info/RECORD
